[
  {
    "date": "2025-08-15",
    "topic": "Q3 Sales Strategy",
    "key_notes": "Discussed new marketing push for 'Zoho Desk'. Germany team to provide feedback on pricing.",
    "action_item": "German distributor to send pricing feedback by Aug 22nd.",
    "status": "Completed"
  },
  {
    "date": "2025-09-10",
    "topic": "Review of 'Zoho Desk' Promotion",
    "key_notes": "Sales are up 15% but some key customers are hesitant. Need to address their specific concerns.",
    "action_item": "Chennai team to prepare a document addressing top 3 customer concerns.",
    "status": "Pending"
  }
]